Html_Builder_Bradley_Hu/__init__.py
Html_Builder_Bradley_Hu/htmlBuilder.py
html_builder_bradley_hu-0.1.0.dist-info/METADATA
html_builder_bradley_hu-0.1.0.dist-info/WHEEL
html_builder_bradley_hu-0.1.0.dist-info/licenses/LICENSE
html_builder_bradley_hu-0.1.0.dist-info/RECORD
