Metadata-Version: 2.4
Name: Html_Builder_Bradley-Hu
Version: 0.1.0
Summary: A package for creating HTML code with Python, driven by a smiple class. Built with Hatchling.
Project-URL: Homepage, https://github.com/bradley-dev777/PythonHtmlBuilder
Project-URL: Issues, https://github.com/bradley-dev777/PythonHtmlBuilder/issues
Author-email: Bradley Hu <hu.yu@wcs-g.com>, "Jayden Yin (Cybersphere World)" <cybersphereworld@gmail.com>
License-Expression: MIT
License-File: LICENSE
Classifier: Operating System :: OS Independent
Classifier: Programming Language :: Python :: 3
Requires-Python: >=3.9
